auth_utils/__init__.py
auth_utils/backends.py
auth_utils/utils.py
auth_utils/tests/__init__.py
auth_utils/tests/test_backends.py
auth_utils/tests/test_utils.py
fastapi_auth_utils-1.1.2.dist-info/LICENSE
fastapi_auth_utils-1.1.2.dist-info/METADATA
fastapi_auth_utils-1.1.2.dist-info/WHEEL
fastapi_auth_utils-1.1.2.dist-info/top_level.txt
fastapi_auth_utils-1.1.2.dist-info/RECORD
