Metadata-Version: 2.1
Name: fastapi-auth-utils
Version: 1.1.2
Summary: Authentication/Authorization utilities for 🚀FastAPI
Author: Alirzea Jafari
Author-email: alirzeaja1384@gmail.com
License: MIT
Classifier: Programming Language :: Python :: 3
Requires-Python: >=3.11
License-File: LICENSE
Requires-Dist: fastapi >=0.101.0
Requires-Dist: PyJWT >=2.8.0
